Metadata-Version: 2.1
Name: Codons
Version: 0.0.10
Summary: Translates and transcribes an arbitrary genetic sequence, generates FASTA-formatted files, and interfaces with BLAST databases to identify genetic and protein sequences.
Home-page: https://github.com/freiburgermsu/codons
Author: Andrew Freiburger
Author-email: andrewfreiburger@gmail.com
License: MIT
Keywords: chemistry,biology,dogma,nucleic,acids,amino,translation,molecular,genetics,transcription,blast,codons
Platform: UNKNOWN
License-File: LICENSE
